gsp_python/__init__.py
gsp_python/__main__.py
gsp_python/dataset_gen.py
gsp_python/gsp.py
gsp_python-0.0.11.dist-info/LICENSE
gsp_python-0.0.11.dist-info/METADATA
gsp_python-0.0.11.dist-info/WHEEL
gsp_python-0.0.11.dist-info/top_level.txt
gsp_python-0.0.11.dist-info/RECORD
