Metadata-Version: 2.1
Name: gsp-python
Version: 0.0.11
Summary: GSP Python implementation
Author: Slocon
Author-email: <79758160+Slocon00@users.noreply.github.com>
Project-URL: Source, https://github.com/Slocon00/GSP-python
Keywords: python,gsp,data mining,sequential pattern mining,sequence mining
Classifier: Programming Language :: Python :: 3
License-File: LICENSE
